azure/planetarycomputer/__init__.py
azure/planetarycomputer/_client.py
azure/planetarycomputer/_configuration.py
azure/planetarycomputer/_patch.py
azure/planetarycomputer/_types.py
azure/planetarycomputer/_version.py
azure/planetarycomputer/py.typed
azure/planetarycomputer/_utils/__init__.py
azure/planetarycomputer/_utils/model_base.py
azure/planetarycomputer/_utils/serialization.py
azure/planetarycomputer/_utils/utils.py
azure/planetarycomputer/aio/__init__.py
azure/planetarycomputer/aio/_client.py
azure/planetarycomputer/aio/_configuration.py
azure/planetarycomputer/aio/_patch.py
azure/planetarycomputer/aio/operations/__init__.py
azure/planetarycomputer/aio/operations/_operations.py
azure/planetarycomputer/aio/operations/_patch.py
azure/planetarycomputer/models/__init__.py
azure/planetarycomputer/models/_enums.py
azure/planetarycomputer/models/_models.py
azure/planetarycomputer/models/_patch.py
azure/planetarycomputer/operations/__init__.py
azure/planetarycomputer/operations/_operations.py
azure/planetarycomputer/operations/_patch.py
azure_planetarycomputer-1.0.0b1.dist-info/licenses/LICENSE
azure_planetarycomputer-1.0.0b1.dist-info/METADATA
azure_planetarycomputer-1.0.0b1.dist-info/WHEEL
azure_planetarycomputer-1.0.0b1.dist-info/top_level.txt
azure_planetarycomputer-1.0.0b1.dist-info/RECORD
